PyJotformAJM/LinkRequester.py
PyJotformAJM/PyJotformAJM.py
PyJotformAJM/SectionsFieldDict.py
PyJotformAJM/Submission.py
PyJotformAJM/__init__.py
PyJotformAJM/_version.py
PyJotformAJM/err.py
pyjotformajm-0.8.dist-info/licenses/LICENSE.txt
pyjotformajm-0.8.dist-info/METADATA
pyjotformajm-0.8.dist-info/WHEEL
pyjotformajm-0.8.dist-info/top_level.txt
pyjotformajm-0.8.dist-info/RECORD
