Metadata-Version: 2.4
Name: PyJotformAJM
Version: 0.8
Summary: *** Overall project description goes here ***
Home-page: https://github.com/amcsparron2793-Water/PyJotformAJM
Download-URL: https://github.com/amcsparron2793-Water/PyJotformAJM/archive/refs/tags/0.8.tar.gz
Author: Amcsparron
Author-email: amcsparron@albanyny.gov
License: MIT License
License-File: LICENSE.txt
Requires-Dist: jotform
Requires-Dist: ApiKeyAJM
Dynamic: author
Dynamic: author-email
Dynamic: download-url
Dynamic: home-page
Dynamic: license
Dynamic: license-file
Dynamic: requires-dist
Dynamic: summary
